requests_httpsproxy/__init__.py
requests_httpsproxy-1.0.6.dist-info/DESCRIPTION.rst
requests_httpsproxy-1.0.6.dist-info/METADATA
requests_httpsproxy-1.0.6.dist-info/RECORD
requests_httpsproxy-1.0.6.dist-info/WHEEL
requests_httpsproxy-1.0.6.dist-info/metadata.json
requests_httpsproxy-1.0.6.dist-info/top_level.txt
requests_httpsproxy-1.0.6.dist-info/zip-safe
