Metadata-Version: 1.1
Name: requests-httpsproxy
Version: 1.0.6
Summary: allow http/https requests through https proxy
Home-page: https://github.com/phuslu/requests_httpsproxy
Author: Phus Lu
Author-email: phuslu@hotmail.com
License: MIT
Keywords: requests https-proxy
Platform: any
Classifier: Development Status :: 4 - Beta
Classifier: License :: OSI Approved :: MIT License
Classifier: Programming Language :: Python :: 2.7
Classifier: Programming Language :: Python :: 3.5
Classifier: Programming Language :: Python :: 3.6
Classifier: Topic :: Internet :: WWW/HTTP
